beni/__init__.py
beni/bbyte.py
beni/bcolor.py
beni/bcrypto.py
beni/bdefine.py
beni/bexecute.py
beni/bfile.py
beni/bform.py
beni/bfunc.py
beni/bhttp.py
beni/bimage.py
beni/binput.py
beni/block.py
beni/blog.py
beni/bpath.py
beni/bplaywright.py
beni/bprogress.py
beni/bqiniu.py
beni/brun.py
beni/bsql.py
beni/bstore.py
beni/btask.py
beni/btime.py
beni/btype.py
beni/bzip.py
beni/resources/temp.md
benimang-0.8.16.dist-info/METADATA
benimang-0.8.16.dist-info/WHEEL
benimang-0.8.16.dist-info/top_level.txt
benimang-0.8.16.dist-info/RECORD
