Metadata-Version: 2.4
Name: benimang
Version: 0.8.16
Summary: Utils library for Beni
Author-email: Beni Mang <benimang@126.com>
Maintainer-email: Beni Mang <benimang@126.com>
Keywords: benimang,beni
Requires-Python: >=3.10
Requires-Dist: aiofiles>=24.1.0
Requires-Dist: aiohttp>=3.12.15
Requires-Dist: async-timeout>=5.0.1
Requires-Dist: chardet>=5.2.0
Requires-Dist: colorama>=0.4.6
Requires-Dist: httpx>=0.28.1
Requires-Dist: orjson>=3.11.3
Requires-Dist: psutil>=7.0.0
Requires-Dist: pyperclip>=1.9.0
Requires-Dist: rich>=14.1.0
Requires-Dist: tzdata>=2025.2
Provides-Extra: full
Requires-Dist: aioconsole>=0.8.1; extra == "full"
Requires-Dist: aiomysql>=0.2.0; extra == "full"
Requires-Dist: aiosqlite>=0.21.0; extra == "full"
Requires-Dist: build>=1.3.0; extra == "full"
Requires-Dist: cryptography>=46.0.1; extra == "full"
Requires-Dist: nest-asyncio>=1.6.0; extra == "full"
Requires-Dist: pillow>=11.3.0; extra == "full"
Requires-Dist: playwright>=1.55.0; extra == "full"
Requires-Dist: prettytable>=3.16.0; extra == "full"
Requires-Dist: pydantic>=2.11.9; extra == "full"
Requires-Dist: pytest>=8.4.2; extra == "full"
Requires-Dist: pytest-asyncio>=1.2.0; extra == "full"
Requires-Dist: pytest-order>=1.3.0; extra == "full"
Requires-Dist: qiniu>=7.17.0; extra == "full"
Requires-Dist: tqdm>=4.67.1; extra == "full"
Requires-Dist: typer>=0.17.4; extra == "full"
